LICENSE
MANIFEST.in
README.md
pyproject.toml
setup.py
output/pypi-readme.md
src/mintalib/__init__.py
src/mintalib/builder.py
src/mintalib/core.c
src/mintalib/expressions.py
src/mintalib/functions.py
src/mintalib/indicators.py
src/mintalib/model.py
src/mintalib/reflib.py
src/mintalib/testing.py
src/mintalib/utils.py
src/mintalib.egg-info/PKG-INFO
src/mintalib.egg-info/SOURCES.txt
src/mintalib.egg-info/dependency_links.txt
src/mintalib.egg-info/requires.txt
src/mintalib.egg-info/top_level.txt
src/mintalib/samples/__init__.py
src/mintalib/samples/daily-prices.csv
src/mintalib/samples/hourly-prices.csv
src/mintalib/samples/minute-prices.csv
tests/test_mintalib.py