Metadata-Version: 2.4
Name: mintalib
Version: 0.0.25
Summary: Minimal Technical Analysis Library for Python
Author-email: Furechan <furechan@xsmail.com>
License: MIT License
Project-URL: homepage, https://github.com/furechan/mintalib
Keywords: cython,technical-analysis,indicators
Classifier: Programming Language :: Python :: 3
Classifier: Operating System :: OS Independent
Requires-Python: >=3.10
License-File: LICENSE
Requires-Dist: numpy
Requires-Dist: pandas
Provides-Extra: polars
Requires-Dist: polars; extra == "polars"
Dynamic: license-file
